azure/mgmt/deviceregistry/__init__.py
azure/mgmt/deviceregistry/_client.py
azure/mgmt/deviceregistry/_configuration.py
azure/mgmt/deviceregistry/_model_base.py
azure/mgmt/deviceregistry/_patch.py
azure/mgmt/deviceregistry/_serialization.py
azure/mgmt/deviceregistry/_validation.py
azure/mgmt/deviceregistry/_version.py
azure/mgmt/deviceregistry/py.typed
azure/mgmt/deviceregistry/aio/__init__.py
azure/mgmt/deviceregistry/aio/_client.py
azure/mgmt/deviceregistry/aio/_configuration.py
azure/mgmt/deviceregistry/aio/_patch.py
azure/mgmt/deviceregistry/aio/operations/__init__.py
azure/mgmt/deviceregistry/aio/operations/_operations.py
azure/mgmt/deviceregistry/aio/operations/_patch.py
azure/mgmt/deviceregistry/models/__init__.py
azure/mgmt/deviceregistry/models/_enums.py
azure/mgmt/deviceregistry/models/_models.py
azure/mgmt/deviceregistry/models/_patch.py
azure/mgmt/deviceregistry/operations/__init__.py
azure/mgmt/deviceregistry/operations/_operations.py
azure/mgmt/deviceregistry/operations/_patch.py
azure_mgmt_deviceregistry-1.0.0.dist-info/LICENSE
azure_mgmt_deviceregistry-1.0.0.dist-info/METADATA
azure_mgmt_deviceregistry-1.0.0.dist-info/WHEEL
azure_mgmt_deviceregistry-1.0.0.dist-info/top_level.txt
azure_mgmt_deviceregistry-1.0.0.dist-info/RECORD
